timetomodel/__init__.py
timetomodel/exceptions.py
timetomodel/featuring.py
timetomodel/forecasting.py
timetomodel/modelling.py
timetomodel/speccing.py
timetomodel/transforming.py
timetomodel/tests/__init__.py
timetomodel/tests/test_forecasting.py
timetomodel/tests/test_series_specs.py
timetomodel/tests/test_timeutils.py
timetomodel/tests/utils.py
timetomodel/utils/__init__.py
timetomodel/utils/debug_utils.py
timetomodel/utils/log_utils.py
timetomodel/utils/time_utils.py
timetomodel-0.7.3.dist-info/LICENSE
timetomodel-0.7.3.dist-info/METADATA
timetomodel-0.7.3.dist-info/WHEEL
timetomodel-0.7.3.dist-info/top_level.txt
timetomodel-0.7.3.dist-info/RECORD
