Metadata-Version: 2.1
Name: timetomodel
Version: 0.7.3
Summary: Sane handling of time series data for forecast modelling - with production usage in mind.
Home-page: https://github.com/seitabv/timetomodel
Author: Seita BV
Author-email: nicolas@seita.nl
License: UNKNOWN
Keywords: time series,forecasting
Platform: UNKNOWN
Classifier: Programming Language :: Python
Classifier: Programming Language :: Python :: 3
Classifier: Development Status :: 3 - Alpha
Classifier: Intended Audience :: Developers
Classifier: License :: OSI Approved :: MIT License
Classifier: Operating System :: OS Independent
Classifier: Topic :: Software Development :: Libraries :: Python Modules
Classifier: Topic :: Scientific/Engineering :: Information Analysis
Requires-Dist: SQLAlchemy
Requires-Dist: matplotlib
Requires-Dist: numpy
Requires-Dist: pandas (>=1.4.0)
Requires-Dist: python-dateutil (>=2.5)
Requires-Dist: pytz
Requires-Dist: scikit-learn
Requires-Dist: scipy
Requires-Dist: statsmodels
